mermaidian/__init__.py
mermaidian/mermaidian.py
mermaidian-0.1.2.dist-info/LICENSE.md
mermaidian-0.1.2.dist-info/METADATA
mermaidian-0.1.2.dist-info/WHEEL
mermaidian-0.1.2.dist-info/top_level.txt
mermaidian-0.1.2.dist-info/RECORD
