Metadata-Version: 2.1
Name: mermaidian
Version: 0.1.2
Summary: Mermaidian is a simple Python interface for using Mermaid.js diagramming capabilities from Python. It can be used from stand-alone Python and also from IPython based notebooks. The core Mermaid.js syntax for writing diagram code is preserved so that the user can always refer to Mermaid.js documentation. However, the creation of the frontmatter for configuration and custom theme is made easier by using a dict instead of YAML encoding.
Home-page: https://github.com/msaudagar/mermaidian
Author: Munawar Saudagar
Author-email: munawar.saudagar@gmail.com
License: MIT
Classifier: Programming Language :: Python :: 3
Classifier: License :: OSI Approved :: MIT License
Classifier: Operating System :: OS Independent
Requires-Python: >=3.9
License-File: LICENSE.md
Requires-Dist: ipython
Requires-Dist: matplotlib
Requires-Dist: numpy
Requires-Dist: opencv-python
Requires-Dist: PyYAML
Requires-Dist: requests
Requires-Dist: pillow
